sinapsis_cotracker/__init__.py
sinapsis_cotracker/helpers/__init__.py
sinapsis_cotracker/helpers/file_downloader.py
sinapsis_cotracker/templates/__init__.py
sinapsis_cotracker/templates/co_tracker_base.py
sinapsis_cotracker/templates/co_tracker_offline.py
sinapsis_cotracker/templates/co_tracker_offline_large.py
sinapsis_cotracker/templates/co_tracker_online.py
sinapsis_cotracker/templates/co_tracker_visualizer.py
sinapsis_cotracker-0.1.5.dist-info/licenses/LICENSE
sinapsis_cotracker-0.1.5.dist-info/METADATA
sinapsis_cotracker-0.1.5.dist-info/WHEEL
sinapsis_cotracker-0.1.5.dist-info/top_level.txt
sinapsis_cotracker-0.1.5.dist-info/RECORD
