Metadata-Version: 2.4
Name: sinapsis-cotracker
Version: 0.1.5
Summary: Templates for multi-object tracking using the CoTracker model, supporting offline, online, and visualization workflows.
Author-email: SinapsisAI <dev@sinapsis.tech>
Project-URL: Homepage, https://sinapsis.tech
Project-URL: Documentation, https://docs.sinapsis.tech/docs
Project-URL: Tutorials, https://docs.sinapsis.tech/tutorials
Project-URL: Repository, https://github.com/Sinapsis-AI/sinapsis-trackers.git
Requires-Python: >=3.10
License-File: LICENSE
Requires-Dist: cotracker
Requires-Dist: flow-vis>=0.1
Requires-Dist: imageio[ffmpeg,pyav]>=2.37.0
Requires-Dist: sinapsis>=0.2.2
Requires-Dist: torch>=2.6.0
Requires-Dist: torchvision>=0.21.0
Requires-Dist: tqdm>=4.67.1
Provides-Extra: all
Requires-Dist: sinapsis-cotracker[sinapsis-data-readers,sinapsis-data-visualization,sinapsis-data-writers]; extra == "all"
Provides-Extra: sinapsis-data-readers
Requires-Dist: sinapsis-data-readers[opencv]>=0.1.2; extra == "sinapsis-data-readers"
Provides-Extra: sinapsis-data-writers
Requires-Dist: sinapsis-data-writers>=0.1.1; extra == "sinapsis-data-writers"
Provides-Extra: sinapsis-data-visualization
Requires-Dist: sinapsis-data-visualization[visualization-matplotlib]>=0.1.2; extra == "sinapsis-data-visualization"
Dynamic: license-file
